Calculator_martynara/__init__.py
Calculator_martynara/calculator_martynara.py
Calculator_martynara/test_calculator.py
calculator_martynara-0.0.2.dist-info/METADATA
calculator_martynara-0.0.2.dist-info/WHEEL
calculator_martynara-0.0.2.dist-info/RECORD
