Metadata-Version: 2.1
Name: Calculator_martynara
Version: 0.0.2
Summary: Calculator
Project-URL: Homepage, https://github.com/pypa/sampleproject
Project-URL: Bug Tracker, https://github.com/pypa/sampleproject/issues
Author-email: Martyna Rastauskaite <rastauskaitemartyna@gmail.com>
Classifier: License :: OSI Approved :: MIT License
Classifier: Operating System :: OS Independent
Classifier: Programming Language :: Python :: 3
Requires-Python: >=3.7
